bitrab/__about__.py
bitrab/__init__.py
bitrab/__main__.py
bitrab/cli.py
bitrab/exceptions.py
bitrab/plan.py
bitrab/config/__init__.py
bitrab/config/loader.py
bitrab/config/schema.py
bitrab/config/validate_pipeline.py
bitrab/execution/__init__.py
bitrab/execution/job.py
bitrab/execution/scheduler.py
bitrab/execution/shell.py
bitrab/execution/variables.py
bitrab/models/__init__.py
bitrab/models/pipeline.py
bitrab/schemas/NOTICE.txt
bitrab/schemas/gitlab_ci_schema.json
bitrab/utils/__init__.py
bitrab/utils/terminal_colors.py
bitrab-0.1.0.dist-info/METADATA
bitrab-0.1.0.dist-info/WHEEL
bitrab-0.1.0.dist-info/entry_points.txt
bitrab-0.1.0.dist-info/licenses/LICENSE
bitrab-0.1.0.dist-info/RECORD
