Metadata-Version: 2.4
Name: bitrab
Version: 0.1.0
Summary: Compile bash to gitlab pipeline yaml
Project-URL: Repository, https://github.com/matthewdeanmartin/bitrab
Project-URL: Documentation, https://bitrab.readthedocs.io/en/latest/
Project-URL: Changelog, https://github.com/matthewdeanmartin/bitrab/blob/main/CHANGELOG.md
Project-URL: homepage, https://github.com/matthewdeanmartin/bitrab
Project-URL: issues, https://github.com/matthewdeanmartin/bitrab/issues/
Author-email: Matthew Martin <matthewdeanmartin@gmail.com>
License-Expression: MIT
License-File: LICENSE
Keywords: bash,gitlab
Classifier: Development Status :: 4 - Beta
Classifier: Intended Audience :: Developers
Classifier: License :: OSI Approved :: MIT License
Classifier: Operating System :: OS Independent
Classifier: Programming Language :: Python
Classifier: Programming Language :: Python :: 3.8
Classifier: Programming Language :: Python :: 3.9
Classifier: Programming Language :: Python :: 3.10
Classifier: Programming Language :: Python :: 3.11
Classifier: Programming Language :: Python :: 3.12
Classifier: Programming Language :: Python :: 3.13
Classifier: Programming Language :: Python :: 3.14
Requires-Python: >=3.8
Requires-Dist: argcomplete
Requires-Dist: certifi
Requires-Dist: colorlog
Requires-Dist: importlib-resources
Requires-Dist: jsonschema
Requires-Dist: orjson
Requires-Dist: packaging
Requires-Dist: rich
Requires-Dist: rtoml; python_version < '3.14'
Requires-Dist: ruamel-yaml
Requires-Dist: textual
Requires-Dist: toml
Requires-Dist: tomli; python_version < '3.11'
Requires-Dist: tomlkit
Requires-Dist: urllib3
